critparse/CriterionMiniSeriesParse.py
critparse/CriterionMovieParse.py
critparse/CriterionParser.py
critparse/OutApi.py
critparse/OutText.py
critparse/__init__.py
critparse/__main__.py
testcritparse/test_CriterionMovieParse.py
testcritparse/test_CriterionParser.py
criterion_site_parser-1.10.dist-info/METADATA
criterion_site_parser-1.10.dist-info/WHEEL
criterion_site_parser-1.10.dist-info/top_level.txt
criterion_site_parser-1.10.dist-info/RECORD
